deltaseis/__init__.py
deltaseis/base_seismic.py
deltaseis/config/__init__.py
deltaseis/data/__init__.py
deltaseis/export/__init__.py
deltaseis/export/export_seismic_segy.py
deltaseis/processing/__init__.py
deltaseis/processing/preprocessing.py
deltaseis/processing/surfacewaves.py
deltaseis/readers/__init__.py
deltaseis/readers/parser_seismic_segy.py
deltaseis/readers/reader_dss_txt.py
deltaseis/readers/reader_grid_to_horizon.py
deltaseis/readers/reader_seismic_seisnc.py
deltaseis/readers/reader_seismic_semd.py
deltaseis/readers/reader_seismic_sg2.py
deltaseis/readers/reader_seismic_tdms.py
deltaseis/tools/__init__.py
deltaseis/tools/convert_segy_seisnc.py
deltaseis/tools/merge.py
deltaseis/tools/moviemaker.py
deltaseis/tools/nans_handler.py
deltaseis/tools/navigation.py
deltaseis/tools/netcdf2xyz.py
deltaseis/tools/segy_editor.py
deltaseis/tools/segy_navigation_despiker.py
deltaseis/tools/segy_navigation_to_shape.py
deltaseis-0.0.5.dist-info/LICENSE
deltaseis-0.0.5.dist-info/METADATA
deltaseis-0.0.5.dist-info/WHEEL
deltaseis-0.0.5.dist-info/top_level.txt
deltaseis-0.0.5.dist-info/RECORD
