Metadata-Version: 2.1
Name: deltaseis
Version: 0.0.5
Summary: Doing cool stuff with seismic data
Maintainer-email: Roeland Nieboer <roeland.nieboer@deltares.nl>
License: MIT License
Project-URL: Homepage, https://github.com/Deltares-research/DeltaSEIS
Project-URL: Repository, https://github.com/Deltares-research/DeltaSEIS.git
Project-URL: Issues, https://github.com/Deltares-research/DeltaSEIS/issues
Keywords: deltaseis,seisnc,seg-y,seismic,das,tdms,pre-stack,post-stack,geophysics,synthetic specfem,netcdf,subsurface toolbox,deltares
Classifier: Development Status :: 2 - Pre-Alpha
Classifier: Intended Audience :: Science/Research
Classifier: Topic :: Scientific/Engineering :: Physics
Classifier: Topic :: Scientific/Engineering :: Image Processing
Classifier: Topic :: Scientific/Engineering :: Visualization
Classifier: License :: OSI Approved :: MIT License
Classifier: Operating System :: OS Independent
Classifier: Programming Language :: Python
Classifier: Programming Language :: Python :: 3.12
Requires-Python: >=3.12
License-File: LICENSE
Requires-Dist: geost
Requires-Dist: segyio
Requires-Dist: segpy
Requires-Dist: segysak
Requires-Dist: obspy
Provides-Extra: dev
Requires-Dist: black; extra == "dev"
Requires-Dist: pytest; extra == "dev"
Requires-Dist: pytest-cov; extra == "dev"
Requires-Dist: ruff; extra == "dev"
Requires-Dist: sphinx; extra == "dev"
Requires-Dist: sphinx-rtd-theme; extra == "dev"
